webauthn_rp/__init__.py
webauthn_rp/asn1.py
webauthn_rp/attesters.py
webauthn_rp/backends.py
webauthn_rp/builders.py
webauthn_rp/constants.py
webauthn_rp/converters.py
webauthn_rp/errors.py
webauthn_rp/parsers.py
webauthn_rp/registrars.py
webauthn_rp/types.py
webauthn_rp/utils.py
webauthn_rp/validators.py
webauthn_rp/verifiers.py
webauthn_rp-0.0.11.dist-info/LICENSE
webauthn_rp-0.0.11.dist-info/WHEEL
webauthn_rp-0.0.11.dist-info/METADATA
webauthn_rp-0.0.11.dist-info/RECORD
