Metadata-Version: 2.1
Name: webauthn-rp
Version: 0.0.11
Summary: WebAuthn-RP is a Python 3 library to manage credentials that conform to the Web Authentication specification.
Home-page: https://github.com/enceladus-rex/webauthn-rp
License: MIT
Author: enceladus-rex
Requires-Python: >=3.6.1,<4.0.0
Classifier: Development Status :: 4 - Beta
Classifier: License :: OSI Approved :: MIT License
Classifier: Programming Language :: Python :: 3
Classifier: Programming Language :: Python :: 3.7
Classifier: Programming Language :: Python :: 3.8
Classifier: Programming Language :: Python :: 3.9
Classifier: Topic :: Security :: Cryptography
Provides-Extra: examples
Requires-Dist: cbor2 (>=5.2.0,<6.0.0)
Requires-Dist: cryptography (>=3.4.7,<4.0.0)
Requires-Dist: pyasn1 (>=0.4.8,<1.0.0)
Project-URL: Documentation, https://webauthn-rp.readthedocs.io/en/latest/
Project-URL: Repository, https://github.com/enceladus-rex/webauthn-rp
